schurilu/__init__.py
schurilu/krylov/__init__.py
schurilu/krylov/fgmres.py
schurilu/krylov/fgmrez.py
schurilu/krylov/pcg.py
schurilu/krylov/planczos.py
schurilu/preconditioners/__init__.py
schurilu/preconditioners/_base.py
schurilu/preconditioners/fsai.py
schurilu/preconditioners/gemslr.py
schurilu/preconditioners/ilu0.py
schurilu/preconditioners/iluk.py
schurilu/preconditioners/ilut.py
schurilu/reordering/__init__.py
schurilu/reordering/spectral.py
schurilu/utils/__init__.py
schurilu/utils/_helpers.py
schurilu-0.1.1.dist-info/licenses/LICENSE
schurilu-0.1.1.dist-info/METADATA
schurilu-0.1.1.dist-info/WHEEL
schurilu-0.1.1.dist-info/top_level.txt
schurilu-0.1.1.dist-info/RECORD
