Metadata-Version: 2.4
Name: schurilu
Version: 0.1.1
Summary: NumPy/SciPy ILU and Schur-complement preconditioners for fair, reproducible Krylov baselines.
Author-email: Tianshi Xu <txu41@emory.edu>
License: MIT
Project-URL: Homepage, https://github.com/Hitenze/SchurILU
Project-URL: Repository, https://github.com/Hitenze/SchurILU
Project-URL: Issues, https://github.com/Hitenze/SchurILU/issues
Keywords: linear-algebra,sparse-matrix,ilu,preconditioner,krylov,gmres,conjugate-gradient,schur-complement
Classifier: Development Status :: 3 - Alpha
Classifier: Intended Audience :: Science/Research
Classifier: License :: OSI Approved :: MIT License
Classifier: Operating System :: OS Independent
Classifier: Programming Language :: Python :: 3
Classifier: Programming Language :: Python :: 3.8
Classifier: Programming Language :: Python :: 3.9
Classifier: Programming Language :: Python :: 3.10
Classifier: Programming Language :: Python :: 3.11
Classifier: Programming Language :: Python :: 3.12
Classifier: Topic :: Scientific/Engineering :: Mathematics
Requires-Python: >=3.8
License-File: LICENSE
Requires-Dist: numpy>=1.20.0
Requires-Dist: scipy>=1.6.0
Provides-Extra: dev
Requires-Dist: pytest>=7.0.0; extra == "dev"
Requires-Dist: pytest-cov>=4.0.0; extra == "dev"
Provides-Extra: examples
Requires-Dist: matplotlib>=3.5.0; extra == "examples"
Dynamic: license-file
